mycalc/calculator.py
eokjae12-1.0.1.dist-info/METADATA
eokjae12-1.0.1.dist-info/WHEEL
eokjae12-1.0.1.dist-info/top_level.txt
eokjae12-1.0.1.dist-info/RECORD
