Metadata-Version: 2.1
Name: eokjae12
Version: 1.0.1
Summary: nice calc
Home-page: 
Download-URL: 
Author: eokjae
License: UNKNOWN
Platform: UNKNOWN
